sgs_pycycle/__init__.py
sgs_pycycle/__main__.py
sgs_pycycle/client.py
sgs_pycycle/models.py
sgs_pycycle-1.0.0.dist-info/COPYING
sgs_pycycle-1.0.0.dist-info/LICENSE
sgs_pycycle-1.0.0.dist-info/METADATA
sgs_pycycle-1.0.0.dist-info/WHEEL
sgs_pycycle-1.0.0.dist-info/entry_points.txt
sgs_pycycle-1.0.0.dist-info/top_level.txt
sgs_pycycle-1.0.0.dist-info/RECORD
