Metadata-Version: 2.1
Name: sgs-pycycle
Version: 1.0.0
Summary: A Python client and object-mapper for the Oslo Bysykkel API
Home-page: https://github.com/sgs-test/sgs-pycycle
Author: Simeon Simeonov
Author-email: sgs@pichove.org
License: BSD 2-Clause
Project-URL: Bug Reports, https://github.com/sgs-test/sgs-pycycle/issues
Project-URL: Source, https://github.com/sgs-test/sgs-pycycle
Keywords: oslo bikes bicycle api
Platform: UNKNOWN
Classifier: Development Status :: 5 - Production/Stable
Classifier: Intended Audience :: Developers
Classifier: License :: OSI Approved :: BSD License
Classifier: Operating System :: OS Independent
Classifier: Programming Language :: Python :: 3 :: Only
Classifier: Programming Language :: Python :: 3.6
Classifier: Programming Language :: Python :: 3.7
Classifier: Programming Language :: Python :: 3.8
Classifier: Programming Language :: Python :: Implementation
Classifier: Topic :: Internet :: WWW/HTTP
Requires-Python: >=3.6
